CPU_Phase1_Part4/Utilities/encodings_formats.v
 /*________________________________________________________________
  |                                                                |
  |  File Name         -Encoding formats.v                         |
  |  Created By        -Group 01                                   |
  |  Project/ Course   -CO502                                      |
  |  Institute         -University of peradeniya                   |
  |  Date              -05.04.2023                                 |
  |  Discription       - Encoding formats              |
  |________________________________________________________________|
  
  */


// OPCODES
`define LUI_OP 7'b0110111
`define AUIPC_OP 7'b0010111
`define JAL_OP 7'b1101111
`define JALR_OP 7'b1100111
`define B_TYPE_OP 7'b1100011
`define LOAD_OP 7'b0000011
`define STORE_OP 7'b0100011
`define I_TYPE_OP 7'b0010011
`define R_TYPE_OP 7'b0110011



// OP1SEL
`define DATA1 1'b0
`define PC 1'b1

// OP2SEL
`define DATA2 1'b0
`define IMM 1'b1

// REG_WRITE_EN
`define EN 1'b0
`define DIS 1'b1

// WB_SEL
`define ALU 2'b00
`define MEM 2'b01
`define IMM_WB 2'b10
`define PC_4 2'b11

// ALU_OP
`define ADD 5'b00000
`define SUB 5'b00010
`define SLL 5'b00100
`define SLT 5'b01000
`define SLTU 5'b01100
`define XOR 5'b10000
`define SRL 5'b10100
`define SRA 5'b10110
`define OR 5'b11000
`define AND 5'b11100
`define MUL 5'b00001
`define MULH 5'b00101
`define MULHSU 5'b01001
`define MULHU 5'b01101
`define DIV 5'b10001
`define DIVU 5'b10101
`define REM 5'b11001
`define REMU 5'b11101

// BRANCH_JUMP
`define B_BEQ 3'b000
`define B_BNE 3'b001
`define B_NO 3'b010
`define B_J 3'b011
`define B_BLT 3'b100
`define B_BGE 3'b101
`define B_BLTU 3'b110
`define B_BGEU 3'b111

// IMM_SEL
`define U_TYPE 3'b000
`define J_TYPE 3'b001
`define S_TYPE 3'b010
`define B_TYPE 3'b011
`define I_TYPE 3'b100
`define I_SIGNED_TYPE 3'b100
`define I_SHIFT_TYPE 3'b101
`define I_UNSIGNED_TYPE 3'b111

// MEM_READ
`define NO_R 3'b000
`define MR_LB 3'b001
`define MR_LH 3'b010
`define MR_LW 3'b011
`define MR_LBU 3'b100
`define MR_LHU 3'b101

//MEM_WRITE
`define NO_W 2'b00
`define MW_SB 2'b01
`define MW_SH 2'b10
`define MW_SW 2'b11

Register/macros.v
`define assert(sig, val,op) \
    if (sig !== val) begin \
        $display("ASSERTION FAILED in %m: sig != %b [original value %b] in line %0d", val, sig, `__LINE__); \
        $finish; \
    end \
$display("%s Passed!",op);

CPU_Phase1_Part3/CPU_Phase1_Final/RV32IM/Immediate_gen_module/immediate_generate.v
 /*________________________________________________________________
  |                                                                |
  |  File Name         -immediate_generate.v                       |
  |  Created By        -Group  01                                  |
  |  Project/ Course   -CO502                                      |
  |  Institute         -University of peradeniya                   |
  |  Date              -05.04.2023                                 |
  |  Discription       -Immmediate Generation unit for RV32IM      |
  |________________________________________________________________|
  
  */

`include "../Utilities/macros.v"
`include "../Utilities/encodings_formats.v"

module immediate_generate(IMM_SEL,IN, OUT );

    // port declaration
    input [24:0] IN;            // instruction[31:7]
    input [2:0] IMM_SEL;        // immediate select op
    output reg [31:0] OUT;      // sign extended 32-bit value


    wire [31:0]  U_OUT,
                J_OUT,
                B_OUT,
                I_SIGN_OUT,
                I_UNSIGN_OUT,
                S_OUT,
                I_SHIFT_OUT;

    // U Type Immediate
    assign U_OUT[11:0] = {12{1'b0}};
    assign U_OUT[31:12] = IN[24:5];
               
    // J type Immediate
    assign J_OUT[1:0] = 2'b00;        
    assign J_OUT[11:2] = IN[23:14];
    assign J_OUT[12] = IN[13];
    assign J_OUT[20:13] = IN[12:5];
    assign J_OUT[31:21] = {11{IN[24]}};

    // B Type Immediate
    assign B_OUT[1:0] = 2'b00;
    assign B_OUT[5:2] = IN[4:1];
    assign B_OUT[11:6] = IN[23:18];
    assign B_OUT[12] = IN[0];
    assign B_OUT[31:13] = {19{IN[24]}};

    //I Type Immediate
    assign I_SIGN_OUT[11:0] = IN[24:13] ;
    assign I_SIGN_OUT[31:12] = {20{IN[24]}};

    //IU --> unsigned extend Immediate
    assign I_UNSIGN_OUT[11:0] = IN[24:13] ;
    assign I_UNSIGN_OUT[31:12] = {20{1'b0}};

    // S Type Immediate
    assign S_OUT[4:0] = IN[4:0] ;
    assign S_OUT[11:5] = IN[24:18];
    assign S_OUT[31:12] = {20{IN[24]}};

    // SFT 
    assign I_SHIFT_OUT[4:0] = IN[17:13];
    assign I_SHIFT_OUT[31:5] = {27{1'b0}};    
    
    always @(*)
    begin
      
        case(IMM_SEL)
            `U_TYPE: OUT = U_OUT;
            `J_TYPE: OUT = J_OUT;
            `S_TYPE: OUT = S_OUT;
            `B_TYPE: OUT = B_OUT;     
            `I_SIGNED_TYPE: OUT = I_SIGN_OUT;          
            `I_SHIFT_TYPE: OUT = I_SHIFT_OUT;         
            `I_UNSIGNED_TYPE: OUT = I_UNSIGN_OUT;           
            default: OUT = 0 ;  
                                
        endcase
    end

endmodule

CPU_Phase1_Part3/Immediate_gen_module/immediate_generate_tb.v

 /*________________________________________________________________
  |                                                                |
  |  File Name         -immediate_generate_tb.v                    |
  |  Created By        -Group  01                                  |
  |  Project/ Course   -CO502                                      |
  |  Institute         -University of peradeniya                   |
  |  Date              -05.04.2023                                 |
  |  Discription       -Test bench for immediate_generate_tb.v     |
  |________________________________________________________________|
  
  */
`include "../Utilities/macros.v" 
`include "../Utilities/encodings_formats.v"
`include "immediate_generate.v"

module immediate_generate_tb;

    reg [24:0] IN;            // instruction[31:7] -> 24 bits
    reg [2:0] IMM_SEL;        // immediate select op
    wire [31:0] OUT;      // sign extended 32-bit val

   
    immediate_generate immediate_generate_1(IMM_SEL,IN, OUT );

    initial begin
        
        $dumpfile("immediate_generate_wavedata.vcd");
        $dumpvars(0, immediate_generate_tb);
        
        $display("============================================================================");
        $display("                      IMMEDIATE GENERATION  UNIT TESTING");
        $display("=============================================================================");

        #10
        //=====================================
        //          Test 01 -U type
        //=====================================
        
        
        IN = 25'b10110000001110001000_10100; 
        IMM_SEL = `U_TYPE;
        #1
        `Verify(OUT, 32'b10110000001110001000_000000000000,"U type");

        #5
        //=====================================
        //          Test 01 -J type
        //=====================================
        
        IN = 25'b1_0001101110_1_01001110_01010;
        IMM_SEL = `J_TYPE;
        #1
        `Verify(OUT, 32'b11111111111_01001110_1_0001101110_00,"J type");

        #5
        //=====================================
        //          Test 01 -S type
        //=====================================
        IN = 25'b1010010_01001_10100_010_00101;
        IMM_SEL = `S_TYPE;
        #1
        `Verify(OUT, 32'b11111111111111111111_1010010_00101,"S type");

        #5
         //=====================================
        //          Test 01 -B type
        //=====================================
        IN = 25'b1_010000_11011_10101_110_0101_0;
        IMM_SEL = `B_TYPE;
        #1
        `Verify(OUT, 32'b1111111111111111111_0_010000_0101_00,"B type");
 
        #5
          //=====================================
        //          Test 01 -I_SIGNED type
        //=====================================
        IN = 25'b101001001001_10100_010_00101;
        IMM_SEL = `I_SIGNED_TYPE;
        #1
        `Verify(OUT, 32'b11111111111111111111_101001001001,"I_SIGNED type");


        #5
         //=====================================
        //          Test 01 -I_SHIFT type
        //=====================================
        IN = 25'b1010010_01001_10100_010_00101;
        IMM_SEL = `I_SHIFT_TYPE;
        #1
        `Verify(OUT, 32'b000000000000000000000000000_01001,"I_SHIFT");

        #5
          //=====================================
        //          Test 01 -J type
        //=====================================
        IN = 25'b101001001001_10100_010_00101;
        IMM_SEL = `I_UNSIGNED_TYPE;
        #1
        `Verify(OUT, 32'b00000000000000000000_101001001001,"I_UNSIGNED");
       
        $display("=======================All Test cases Passed !!!=============================");

        $finish;
    end

endmodule

CPU_Phase1_Part3/Immediate_gen_module/immediate_generate_wavedata.vcd
$date
	Wed May 24 21:19:22 2023
$end
$version
	Icarus Verilog
$end
$timescale
	1s
$end
$scope module immediate_generate_tb $end
$var wire 32 ! OUT [31:0] $end
$var reg 3 " IMM_SEL [2:0] $end
$var reg 25 # IN [24:0] $end
$scope module immediate_generate_1 $end
$var wire 3 $ IMM_SEL [2:0] $end
$var wire 25 % IN [24:0] $end
$var wire 32 & U_OUT [31:0] $end
$var wire 32 ' S_OUT [31:0] $end
$var wire 32 ( J_OUT [31:0] $end
$var wire 32 ) I_UNSIGN_OUT [31:0] $end
$var wire 32 * I_SIGN_OUT [31:0] $end
$var wire 32 + I_SHIFT_OUT [31:0] $end
$var wire 32 , B_OUT [31:0] $end
$var reg 32 - OUT [31:0] $end
$upscope $end
$upscope $end
$enddefinitions $end
#0
$dumpvars
b0 -
bx00 ,
b0xxxxx +
bx *
b0xxxxxxxxxxxx )
bx00 (
bx '
bx000000000000 &
bx %
bx $
bx #
bx "
b0 !
$end
#10
b10110000001110001000000000000000 !
b10110000001110001000000000000000 -
b10110000001110001000000000000000 &
b11111111111100010001011000000100 (
b11111111111111111110011000101000 ,
b11111111111111111111101100000011 *
b101100000011 )
b11111111111111111111101100010100 '
b11 +
b0 "
b0 $
b1011000000111000100010100 #
b1011000000111000100010100 %
#16
b11111111111010011101000110111000 !
b11111111111010011101000110111000 -
b10001101110101001110000000000000 &
b11111111111010011101000110111000 (
b11111111111111111110000110010100 ,
b11111111111111111111100011011101 *
b100011011101 )
b11111111111111111111100011001010 '
b11101 +
b1 "
b1 $
b1000110111010100111001010 #
b1000110111010100111001010 %
#22
b11111111111111111111101001000101 !
b11111111111111111111101001000101 -
b10100100100110100010000000000000 &
b11111111111101000101010010010000 (
b11111111111111111111010010001000 ,
b11111111111111111111101001001001 *
b101001001001 )
b11111111111111111111101001000101 '
b1001 +
b10 "
b10 $
b1010010010011010001000101 #
b1010010010011010001000101 %
#28
b11111111111111111110010000010100 !
b11111111111111111110010000010100 -
b10100001101110101110000000000000 &
b11111111111101011101010000110100 (
b11111111111111111110010000010100 ,
b11111111111111111111101000011011 *
b101000011011 )
b11111111111111111111101000001010 '
b11011 +
b11 "
b11 $
b1010000110111010111001010 #
b1010000110111010111001010 %
#34
b11111111111111111111101001001001 !
b11111111111111111111101001001001 -
b10100100100110100010000000000000 &
b11111111111101000101010010010000 (
b11111111111111111111010010001000 ,
b11111111111111111111101001001001 *
b101001001001 )
b11111111111111111111101001000101 '
b1001 +
b100 "
b100 $
b1010010010011010001000101 #
b1010010010011010001000101 %
#40
b1001 !
b1001 -
b101 "
b101 $
#46
b101001001001 !
b101001001001 -
b111 "
b111 $
